{
  "name": "A. String Building",
  "testType": "MULTI_NUMBER",
  "input": {
    "type": "STANDARD",
    "fileName": "input.txt"
  },
  "output": {
    "type": "STANDARD",
    "fileName": "output.txt"
  },
  "tests": [
    {
      "input": "8\naaaabbb\nbbaaaaabbb\naaaaaa\nabab\na\nb\naaaab\nbbaaa\n",
      "output": "YES\nYES\nYES\nNO\nNO\nNO\nNO\nYES\n",
      "index": 0,
      "active": true
    }
  ],
  "location": "src/codes",
  "vmArgs": "-Xmx512M",
  "mainClass": "Main",
  "taskClass": "codes.AStringBuilding",
  "checkerClass": "net.egork.chelper.checkers.TokenChecker",
  "checkerParameters": "",
  "testClasses": [],
  "date": "2022.04.22",
  "contestName": "Codeforces - Educational Codeforces Round 127 (Rated for Div. 2)",
  "truncate": true,
  "inputClass": "net.cplibrary.io.InputReader",
  "outputClass": "net.cplibrary.io.OutputWriter",
  "includeLocale": false,
  "failOnOverflow": false,
  "interactive": false,
  "interactor": "net.egork.chelper.tester.Interactor"
}