{
  "name": "B - Easter Eggs",
  "testType": "SINGLE",
  "input": {
    "type": "STANDARD",
    "fileName": "input.txt"
  },
  "output": {
    "type": "STANDARD",
    "fileName": "output.txt"
  },
  "tests": [
    {
      "input": "8\n",
      "output": "ROYGRBIV\n",
      "index": 0,
      "active": true
    },
    {
      "input": "13\n",
      "output": "ROYGBIVGBIVYG\n",
      "index": 1,
      "active": true
    }
  ],
  "location": "src/codes",
  "vmArgs": "-Xmx256M",
  "mainClass": "Main",
  "taskClass": "codes.TaskB",
  "checkerClass": "net.egork.chelper.checkers.TokenChecker",
  "checkerParameters": "",
  "testClasses": [],
  "date": "2021.06.22",
  "contestName": "Codeforces Beta Round #70 (Div. 2)",
  "truncate": true,
  "inputClass": "net.egork.io.InputReader",
  "outputClass": "net.egork.io.OutputWriter",
  "includeLocale": false,
  "failOnOverflow": false,
  "interactive": false,
  "interactor": "net.egork.chelper.tester.Interactor"
}