{
  "name": "B. Make it Divisible by 25",
  "testType": "MULTI_NUMBER",
  "input": {
    "type": "STANDARD",
    "fileName": "input.txt"
  },
  "output": {
    "type": "STANDARD",
    "fileName": "output.txt"
  },
  "tests": [
    {
      "input": "5\n100\n71345\n3259\n50555\n2050047\n",
      "output": "0\n3\n1\n3\n2\n",
      "index": 0,
      "active": true
    }
  ],
  "location": "src/codes",
  "vmArgs": "-Xmx256M",
  "mainClass": "Main",
  "taskClass": "codes.BMakeItDivisibleBy25",
  "checkerClass": "net.egork.chelper.checkers.TokenChecker",
  "checkerParameters": "",
  "testClasses": [],
  "date": "2021.11.04",
  "contestName": "Codeforces - Codeforces Round #748 (Div. 3)",
  "truncate": true,
  "inputClass": "net.cplibrary.io.InputReader",
  "outputClass": "net.cplibrary.io.OutputWriter",
  "includeLocale": false,
  "failOnOverflow": false,
  "interactive": false,
  "interactor": "net.egork.chelper.tester.Interactor"
}